classes/tools.py
natural_history_museum_mcp/__init__.py
natural_history_museum_mcp/__main__.py
natural_history_museum_mcp/constants.py
natural_history_museum_mcp/nhm_api.py
natural_history_museum_mcp/server.py
natural_history_museum_mcp-0.1.22.dist-info/METADATA
natural_history_museum_mcp-0.1.22.dist-info/WHEEL
natural_history_museum_mcp-0.1.22.dist-info/entry_points.txt
natural_history_museum_mcp-0.1.22.dist-info/top_level.txt
natural_history_museum_mcp-0.1.22.dist-info/RECORD
