Metadata-Version: 2.4
Name: natural-history-museum-mcp
Version: 0.1.22
Summary: MCP server for the British Natural History Museum data API
Requires-Python: >=3.13
Requires-Dist: mcp[cli]>=1.4.1
Requires-Dist: nhm-pyportal>=0.1
Requires-Dist: pytest>=8.3.5
Requires-Dist: requests>=2.32.3
